asynqueue/__init__.py
asynqueue/base.py
asynqueue/errors.py
asynqueue/info.py
asynqueue/interfaces.py
asynqueue/iteration.py
asynqueue/misc.py
asynqueue/null.py
asynqueue/process.py
asynqueue/tasks.py
asynqueue/threads.py
asynqueue/util.py
asynqueue/va.py
asynqueue/wire.py
asynqueue/workers.py
asynqueue/test/__init__.py
asynqueue/test/test_base.py
asynqueue/test/test_info.py
asynqueue/test/test_interfaces.py
asynqueue/test/test_iteration.py
asynqueue/test/test_process.py
asynqueue/test/test_tasks.py
asynqueue/test/test_threads.py
asynqueue/test/test_util.py
asynqueue/test/test_wire.py
asynqueue/test/test_workers.py
asynqueue/test/testbase.py
asynqueue-0.9.9.dist-info/licenses/LICENSE.txt
asynqueue-0.9.9.dist-info/licenses/NOTICE
asynqueue-0.9.9.dist-info/METADATA
asynqueue-0.9.9.dist-info/WHEEL
asynqueue-0.9.9.dist-info/top_level.txt
asynqueue-0.9.9.dist-info/RECORD
