Metadata-Version: 2.4
Name: AsynQueue
Version: 0.9.9
Summary: Asynchronous task queueing with Twisted: threaded, multicore, and remote.
Home-page: http://edsuom.com/AsynQueue.html
Author: Edwin A. Suominen
Author-email: foss@edsuom.com
Maintainer: Edwin A. Suominen
Maintainer-email: foss@edsuom.com
License: Apache License (2.0)
Project-URL: GitHub, https://github.com/edsuom/AsynQueue
Project-URL: API, http://edsuom.com/AsynQueue/asynqueue.html
Keywords: twisted,asynchronous,async,defer,deferred,threads,parallel,distributed,task,queue,priority,multicore
Platform: OS Independent
Classifier: Development Status :: 5 - Production/Stable
Classifier: Intended Audience :: Developers
Classifier: Intended Audience :: Science/Research
Classifier: License :: OSI Approved :: Apache Software License
Classifier: Operating System :: OS Independent
Classifier: Programming Language :: Python :: 3.9
Classifier: Framework :: Twisted
Classifier: Topic :: System :: Clustering
Classifier: Topic :: System :: Distributed Computing
Classifier: Topic :: Software Development :: Libraries :: Python Modules
Classifier: Topic :: System :: Hardware :: Symmetric Multi-processing
License-File: LICENSE.txt
License-File: NOTICE
Requires-Dist: Twisted
Requires-Dist: six
Dynamic: author
Dynamic: author-email
Dynamic: classifier
Dynamic: description
Dynamic: description-content-type
Dynamic: home-page
Dynamic: keywords
Dynamic: license
Dynamic: license-file
Dynamic: maintainer
Dynamic: maintainer-email
Dynamic: platform
Dynamic: project-url
Dynamic: requires-dist
Dynamic: summary
